Workbook

Sheet Assumptions
A1: Northline — three-statement model (fictional, annual)
A3: Item | B3: Year 1 | C3: Year 2 | D3: Year 3
A4: Revenue | B4: 12000000 | C4: 13200000 | D4: 14520000
A5: COGS % of revenue | B5: 0.61 | C5: 0.605 | D5: 0.6
A6: OpEx (ex-D&A) | B6: 2800000 | C6: 2940000 | D6: 3080000
A7: D&A | B7: 420000 | C7: 450000 | D7: 480000
A8: Interest | B8: 180000 | C8: 165000 | D8: 150000
A9: Tax rate | B9: 0.21 | C9: 0.21 | D9: 0.21
A10: Capex | B10: 500000 | C10: 480000 | D10: 460000
A11: Change in NWC (use of cash if +) | B11: 150000 | C11: 120000 | D11: 90000
A12: Debt issued / (repaid) | B12: -200000 | C12: -200000 | D12: -200000
A13: Dividends | B13: 0 | C13: 0 | D13: 0
A14: Opening cash | B14: 650000 | C14: =IS!C15 -> 0 | D14: =IS!D15 -> 0
A15: Opening net PP&E | B15: 3200000 | C15: = | D15: =
A16: Opening debt | B16: 1800000
A17: Opening equity | B17: 2500000

Sheet IS
A1: Income statement
A3: Line | B3: Year 1 | C3: Year 2 | D3: Year 3
A4: Revenue | B4: =Assumptions!B4 -> 12000000 | C4: =Assumptions!C4 -> 13200000 | D4: =Assumptions!D4 -> 14520000
A5: COGS | B5: =B4*Assumptions!B5 -> 7320000 | C5: =C4*Assumptions!C5 -> 7986000 | D5: =D4*Assumptions!D5 -> 8712000
A6: Gross profit | B6: =B4-B5 -> 4680000 | C6: =C4-C5 -> 5214000 | D6: =D4-D5 -> 5808000
A7: OpEx (ex-D&A) | B7: =Assumptions!B6 -> 2800000 | C7: =Assumptions!C6 -> 2940000 | D7: =Assumptions!D6 -> 3080000
A8: D&A | B8: =Assumptions!B7 -> 420000 | C8: =Assumptions!C7 -> 450000 | D8: =Assumptions!D7 -> 480000
A9: EBIT | B9: =B6-B7-B8 -> 1460000 | C9: =C6-C7-C8 -> 1824000 | D9: =D6-D7-D8 -> 2248000
A10: Interest | B10: =Assumptions!B8 -> 180000 | C10: =Assumptions!C8 -> 165000 | D10: =Assumptions!D8 -> 150000
A11: EBT | B11: =B9-B10 -> 1280000 | C11: =C9-C10 -> 1659000 | D11: =D9-D10 -> 2098000
A12: Tax | B12: =B11*Assumptions!B9 -> 268800 | C12: =C11*Assumptions!C9 -> 348390 | D12: =D11*Assumptions!D9 -> 440580
A13: Net income | B13: =B11-B12 -> 1011200 | C13: =C11-C12 -> 1310610 | D13: =D11-D12 -> 1657420

Sheet CF
A1: Cash flow
A3: Line | B3: Year 1 | C3: Year 2 | D3: Year 3
A4: Net income | B4: =IS!B13 -> 1011200 | C4: =IS!C13 -> 1310610 | D4: =IS!D13 -> 1657420
A5: + D&A | B5: =IS!B8 -> 420000 | C5: =IS!C8 -> 450000 | D5: =IS!D8 -> 480000
A6: − Increase in NWC | B6: =-Assumptions!B11 -> -150000 | C6: =-Assumptions!C11 -> -120000 | D6: =-Assumptions!D11 -> -90000
A7: CFO | B7: =B4+B5+B6 -> 1281200 | C7: =C4+C5+C6 -> 1640610 | D7: =D4+D5+D6 -> 2047420
A8: Capex | B8: =-Assumptions!B10 -> -500000 | C8: =-Assumptions!C10 -> -480000 | D8: =-Assumptions!D10 -> -460000
A9: CFI | B9: =B8 -> -500000 | C9: =C8 -> -480000 | D9: =D8 -> -460000
A10: Debt issued/(repaid) | B10: =Assumptions!B12 -> -200000 | C10: =Assumptions!C12 -> -200000 | D10: =Assumptions!D12 -> -200000
A11: Dividends | B11: =-Assumptions!B13 -> 0 | C11: =-Assumptions!C13 -> 0 | D11: =-Assumptions!D13 -> 0
A12: CFF | B12: =B10+B11 -> -200000 | C12: =C10+C11 -> -200000 | D12: =D10+D11 -> -200000
A13: Net change in cash | B13: =B7+B9+B12 -> 581200 | C13: =C7+C9+C12 -> 960610 | D13: =D7+D9+D12 -> 1387420
A14: Opening cash | B14: =Assumptions!B14 -> 650000 | C14: =B15 -> 1231200 | D14: =C15 -> 2191810
A15: Ending cash | B15: =B14+B13 -> 1231200 | C15: =C14+C13 -> 2191810 | D15: =D14+D13 -> 3579230

Sheet BS
A1: Balance sheet
A3: Line | B3: Year 1 | C3: Year 2 | D3: Year 3
A4: Cash | B4: =CF!B15 -> 1231200 | C4: =CF!C15 -> 2191810 | D4: =CF!D15 -> 3579230
A5: Net working capital | B5: =900000+Assumptions!B11 -> 1050000 | C5: =B5+Assumptions!C11 -> 1170000 | D5: =C5+Assumptions!D11 -> 1260000
A6: Net PP&E | B6: =Assumptions!B15+Assumptions!B10-IS!B8 -> 3280000 | C6: =B6+Assumptions!C10-IS!C8 -> 3310000 | D6: =C6+Assumptions!D10-IS!D8 -> 3290000
A7: Total assets | B7: =B4+B5+B6 -> 5561200 | C7: =C4+C5+C6 -> 6671810 | D7: =D4+D5+D6 -> 8129230
A9: Debt | B9: =Assumptions!B16+Assumptions!B12 -> 1600000 | C9: =B9+Assumptions!C12 -> 1400000 | D9: =C9+Assumptions!D12 -> 1200000
A10: Equity | B10: =Assumptions!B17+IS!B13-Assumptions!B13 -> 3511200 | C10: =B10+IS!C13-Assumptions!C13 -> 4821810 | D10: =C10+IS!D13-Assumptions!D13 -> 6479230
A11: Total liabilities & equity | B11: =B9+B10 -> 5111200 | C11: =C9+C10 -> 6221810 | D11: =D9+D10 -> 7679230
A13: Balance check (must be 0) | B13: =B7-B11 -> 450000 | C13: =C7-C11 -> 450000 | D13: =D7-D11 -> 450000

Sheet Notes
A1: How the statements link
A3: Net income flows to cash flow and to equity.
A4: D&A is added back in cash flow and reduces net PP&E.
A5: Capex increases PP&E and is a use of cash.
A6: Debt issued / repaid hits cash and the debt line.
A7: Ending cash on CF is the cash line on the balance sheet.
A8: Balance check must stay 0. If it is not 0 after you edit inputs, a link broke.
